{
  "name": "I",
  "s": {
    "name": "G",
    "s": {
      "name": "E",
      "s": {
        "name": "C",
        "s": {
          "name": "A"
        },
        "d": {
          "name": "B"
        }
      },
      "d": {
        "name": "D",
        "s": {
          "name": "A"
        },
        "d": {
          "name": "B"
        }
      }
    },
    "d": {
      "name": "F",
      "s": {
        "name": "C",
        "s": {
          "name": "A"
        },
        "d": {
          "name": "B"
        }
      },
      "d": {
        "name": "D",
        "s": {
          "name": "A"
        },
        "d": {
          "name": "B"
        }
      }
    }
  },
  "d": {
    "name": "H",
    "s": {
      "name": "E",
      "s": {
        "s": {
          "name": "A"
        },
        "d": {
          "name": "B"
        },
        "name": "C"
      },
      "d": {
        "s": {
          "name": "A"
        },
        "d": {
          "name": "B"
        },
        "name": "D"
      }
    },
    "d": {
      "name": "F",
      "s": {
        "s": {
          "name": "A"
        },
        "d": {
          "name": "B"
        },
        "name": "C"
      },
      "d": {
        "s": {
          "name": "A"
        },
        "d": {
          "name": "B"
        },
        "name": "D"
      }
    }
  }
}